{
  "project_info": {
    "project_number": "829864325452",
    "firebase_url": "https://acheivagamap-e1da7.firebaseio.com",
    "project_id": "acheivagamap-e1da7",
    "storage_bucket": "acheivagamap-e1da7.appspot.com"
  },
  "client": [
    {
      "client_info": {
        "mobilesdk_app_id": "1:829864325452:android:7cdef69c0d734d95",
        "android_client_info": {
          "package_name": "com.example.wanderson.acheivagamap"
        }
      },
      "oauth_client": [
        {
          "client_id": "829864325452-j7og2oiv05kn7a3bn5job65ni1iim4ac.apps.googleusercontent.com",
          "client_type": 1,
          "android_info": {
            "package_name": "com.example.wanderson.acheivagamap",
            "certificate_hash": "6127918eff8b1afa1cb34a88123d634a510e7f71"
          }
        },
        {
          "client_id": "829864325452-c8scegdkj26b5hu9di7ufesrc6tlgj50.apps.googleusercontent.com",
          "client_type": 3
        }
      ],
      "api_key": [
        {
          "current_key": "AIzaSyCUCaHUXE5AyMsEgnvxHE9npgGct-vd2AE"
        }
      ],
      "services": {
        "analytics_service": {
          "status": 1
        },
        "appinvite_service": {
          "status": 2,
          "other_platform_oauth_client": [
            {
              "client_id": "829864325452-c8scegdkj26b5hu9di7ufesrc6tlgj50.apps.googleusercontent.com",
              "client_type": 3
            }
          ]
        },
        "ads_service": {
          "status": 2
        }
      }
    }
  ],
  "configuration_version": "1"
}